neuralfoil/README.md
neuralfoil/__init__.py
neuralfoil/gen1_architecture/CL_linear_regression.py
neuralfoil/gen1_architecture/__init__.py
neuralfoil/gen1_architecture/main.py
neuralfoil/gen1_architecture/nn_weights_and_biases/nn-large.npz
neuralfoil/gen1_architecture/nn_weights_and_biases/nn-medium.npz
neuralfoil/gen1_architecture/nn_weights_and_biases/nn-small.npz
neuralfoil/gen1_architecture/nn_weights_and_biases/nn-xlarge.npz
neuralfoil/gen1_architecture/nn_weights_and_biases/nn-xsmall.npz
neuralfoil/gen1_architecture/nn_weights_and_biases/nn-xxlarge.npz
neuralfoil/gen1_architecture/nn_weights_and_biases/nn-xxsmall.npz
neuralfoil/gen1_architecture/nn_weights_and_biases/nn-xxxlarge.npz
neuralfoil/gen2_5_architecture/__init__.py
neuralfoil/gen2_5_architecture/_basic_data_type.py
neuralfoil/gen2_5_architecture/main.py
neuralfoil/gen2_5_architecture/nn_weights_and_biases/nn-large.npz
neuralfoil/gen2_5_architecture/nn_weights_and_biases/nn-medium.npz
neuralfoil/gen2_5_architecture/nn_weights_and_biases/nn-small.npz
neuralfoil/gen2_5_architecture/nn_weights_and_biases/nn-xlarge.npz
neuralfoil/gen2_5_architecture/nn_weights_and_biases/nn-xsmall.npz
neuralfoil/gen2_5_architecture/nn_weights_and_biases/nn-xxlarge.npz
neuralfoil/gen2_5_architecture/nn_weights_and_biases/nn-xxsmall.npz
neuralfoil/gen2_5_architecture/nn_weights_and_biases/nn-xxxlarge.npz
neuralfoil/gen2_5_architecture/nn_weights_and_biases/scaled_input_distribution.npz
neuralfoil/gen2_architecture/__init__.py
neuralfoil/gen2_architecture/_basic_data_type.py
neuralfoil/gen2_architecture/main.py
neuralfoil/gen2_architecture/nn_weights_and_biases/nn-large.npz
neuralfoil/gen2_architecture/nn_weights_and_biases/nn-medium.npz
neuralfoil/gen2_architecture/nn_weights_and_biases/nn-small.npz
neuralfoil/gen2_architecture/nn_weights_and_biases/nn-xlarge.npz
neuralfoil/gen2_architecture/nn_weights_and_biases/nn-xsmall.npz
neuralfoil/gen2_architecture/nn_weights_and_biases/nn-xxlarge.npz
neuralfoil-0.3.1.dist-info/LICENSE.txt
neuralfoil-0.3.1.dist-info/METADATA
neuralfoil-0.3.1.dist-info/WHEEL
neuralfoil-0.3.1.dist-info/top_level.txt
neuralfoil-0.3.1.dist-info/RECORD
