Metadata-Version: 2.2
Name: NeuralFoil
Version: 0.3.1
Summary: NeuralFoil is an airfoil aerodynamics analysis tool using physics-informed machine learning, in pure Python/NumPy.
Home-page: https://github.com/peterdsharpe/NeuralFoil
Author: Peter Sharpe
Author-email: pds@mit.edu
Project-URL: Source, https://github.com/peterdsharpe/NeuralFoil
Project-URL: Bug Reports, https://github.com/peterdsharpe/NeuralFoil/issues
Keywords: python machine learning analysis optimization aerospace airplane cfd aircraft hydrodynamics aerodynamics sailing propeller airfoil xfoil design mdo mdao physics informed neural network
Classifier: Development Status :: 5 - Production/Stable
Classifier: Intended Audience :: Science/Research
Classifier: Topic :: Scientific/Engineering :: Physics
Classifier: License :: OSI Approved :: MIT License
Classifier: Programming Language :: Python :: 3
Requires-Python: >=3.9
License-File: LICENSE.txt
Requires-Dist: numpy>=1
Requires-Dist: aerosandbox<4.3.0,>=4.2.4
Provides-Extra: training
Requires-Dist: torch; extra == "training"
Requires-Dist: ray; extra == "training"
Requires-Dist: polars; extra == "training"
Requires-Dist: tqdm; extra == "training"
Provides-Extra: test
Requires-Dist: pytest; extra == "test"
Requires-Dist: nbval; extra == "test"
Provides-Extra: docs
Requires-Dist: sphinx; extra == "docs"
Requires-Dist: furo; extra == "docs"
Requires-Dist: sphinx-autoapi; extra == "docs"
Dynamic: author
Dynamic: author-email
Dynamic: classifier
Dynamic: description
Dynamic: description-content-type
Dynamic: home-page
Dynamic: keywords
Dynamic: project-url
Dynamic: provides-extra
Dynamic: requires-dist
Dynamic: requires-python
Dynamic: summary
